pynauriz/__init__.py
pynauriz/contrib/__init__.py
pynauriz/contrib/django/__init__.py
pynauriz/contrib/django/choices.py
pynauriz/utils/__init__.py
pynauriz/utils/log_filters.py
pynauriz/utils/redis_manager.py
pynauriz/utils/task_locks.py
pynauriz-0.4.0.dist-info/LICENSE
pynauriz-0.4.0.dist-info/METADATA
pynauriz-0.4.0.dist-info/WHEEL
pynauriz-0.4.0.dist-info/top_level.txt
pynauriz-0.4.0.dist-info/RECORD
