Metadata-Version: 2.2
Name: pynauriz
Version: 0.4.0
Summary: Набор полезных инструментов и утилит для Python.
Home-page: https://github.com/NaurizAitbai/pynauriz
Author: Naurizbek Aitbaev
Author-email: nauriz.aitbai@gmail.com
License: MIT
Classifier: Programming Language :: Python :: 3
Classifier: License :: OSI Approved :: MIT License
Classifier: Operating System :: OS Independent
Requires-Python: >=3.6
License-File: LICENSE
Dynamic: author
Dynamic: author-email
Dynamic: classifier
Dynamic: description
Dynamic: description-content-type
Dynamic: home-page
Dynamic: license
Dynamic: requires-python
Dynamic: summary
